LMtorch/LMtorch.py
LMtorch/__init__.py
LMtorch-0.0.0.dist-info/LICENSE.txt
LMtorch-0.0.0.dist-info/METADATA
LMtorch-0.0.0.dist-info/WHEEL
LMtorch-0.0.0.dist-info/top_level.txt
LMtorch-0.0.0.dist-info/RECORD
